{
  "name": "The Invisible Man",
  "year": 2020,
  "runtime": 124,
  "categories": ["Horror", "Mystery", "Sci-Fi", "Thriller"],
  "release-date": "2020-03-01",
  "director": "Leigh Whannell",
  "writer": ["Leigh Whannell", "Leigh Whannell"],
  "actors": ["Elisabeth Moss", "Oliver Jackson-Cohen", "Harriet Dyer"],
  "storyline": "When Cecilia's abusive ex takes his own life and leaves her his fortune, she suspects his death was a hoax. As a series of coincidences turn lethal, Cecilia works to prove that she is being hunted by someone nobody can see. "
}
